..travis.yml.un~
.MANIFEST.in.un~
.README.md.swp
.README.md.un~
.README.rst.un~
.__init__.py.un~
.appveyor.yml.un~
.coverage
.gitignore
.requirements.txt.un~
.setup.py.swp
.setup.py.un~
.tox.ini.un~
.travis.yml
.travis.yml.orig
.travis.yml~
LICENSE
MANIFEST.in
MANIFEST.in.orig
README.md
README.md.orig
README.md~
README.rst
README.rst.orig
README.rst~
appveyor.yml
appveyor.yml.orig
appveyor.yml~
requirements.txt
requirements.txt.orig
setup.py
setup.py.orig
setup.py~
tox.ini
tox.ini.orig
tox.ini~
appveyor/install.ps1
appveyor/run_with_env.cmd
seqfile/.__init__.py.un~
seqfile/.seqfile.py.swp
seqfile/.seqfile.py.un~
seqfile/.test.py.un~
seqfile/.tests.py.swo
seqfile/.tests.py.swp
seqfile/.tests.py.un~
seqfile/__init__.py
seqfile/__init__.py.orig
seqfile/__init__.py~
seqfile/seqfile.py
seqfile/seqfile.py.orig
seqfile/seqfile.py~
seqfile/tests.py
seqfile/tests.py.orig
seqfile/tests.py~
seqfile.egg-info/PKG-INFO
seqfile.egg-info/SOURCES.txt
seqfile.egg-info/dependency_links.txt
seqfile.egg-info/entry_points.txt
seqfile.egg-info/requires.txt
seqfile.egg-info/top_level.txt
seqfile.egg-info/zip-safe