Metadata-Version: 1.1
Name: seqfile
Version: 0.2.0
Summary: Find the next file in a sequence of files in a thread-safe way.
Home-page: https://github.com/musically-ut/seqfile
Author: Utkarsh Upadhyay
Author-email: musically.ut@gmail.com
License: MIT
Keywords: file threadsafe sequence
Platform: UNKNOWN
Classifier: License :: OSI Approved :: MIT License
Classifier: Intended Audience :: Developers
Classifier: Intended Audience :: Science/Research
Classifier: Development Status :: 3 - Alpha
Classifier: Operating System :: OS Independent
Classifier: Topic :: Utilities
Classifier: License :: OSI Approved :: MIT License
Classifier: Programming Language :: Python :: 2.6
Classifier: Programming Language :: Python :: 2.7
Classifier: Programming Language :: Python :: 3.3
Classifier: Programming Language :: Python :: 3.4
Classifier: Natural Language :: English
